scripts/scripts/verilog/dff/dff.v
//==============================================================================
// Filename: dff.v
// Author:   Cody Cziesler
//
// Description: A model of a D Flip-Flop
//==============================================================================
module dff (
  input  wire  clk,
  input  wire  rst_n,
  input  wire  d,
  output reg   q
);

always @(posedge clk or negedge rst_n) begin
  if (~rst_n) begin
    q <= 1'b0;
  end else begin
    q <= d;
  end
end

endmodule

scripts/scripts/verilog/dff/tb_dff.sv
module tb_dff ();

bit  clk;
bit  rst_n;
bit  d;
wire q;

always #5 clk = ~clk;

initial begin
  $monitor(clk, rst_n, d, q);
      rst_n = 1'b0;
  #10 rst_n = 1'b1;

  #1000 $finish();
end

initial begin
  $dumpfile("tb_dff.vcd");
  $dumpvars(0,tb_dff);
end


always #6 d = $random();

dff dut (.*);

endmodule

scripts/scripts/verilog/dff/tb_dff.vcd
$date
	Mon Dec  9 21:33:18 2013
$end
$version
	Icarus Verilog
$end
$timescale
	1s
$end
$scope module tb_dff $end
$var wire 1 ! q $end
$var reg 1 " clk $end
$var reg 1 # d $end
$var reg 1 $ rst_n $end
$scope module dut $end
$var wire 1 " clk $end
$var wire 1 # d $end
$var wire 1 $ rst_n $end
$var reg 1 ! q $end
$upscope $end
$upscope $end
$enddefinitions $end
#0
$dumpvars
0$
0#
0"
x!
$end
#5
0!
1"
#10
0"
1$
#12
1#
#15
1!
1"
#20
0"
#25
1"
#30
0"
#35
1"
#40
0"
#45
1"
#48
0#
#50
0"
#54
1#
#55
1"
#60
0"
#65
1"
#66
0#
#70
0"
#72
1#
#75
1"
#80
0"
#84
0#
#85
0!
1"
#90
0"
1#
#95
1!
1"
#96
0#
#100
0"
#102
1#
#105
1"
#108
0#
#110
0"
#114
1#
#115
1"
#120
0"
#125
1"
#126
0#
#130
0"
#132
1#
#135
1"
#138
0#
#140
0"
#145
0!
1"
#150
0"
#155
1"
#156
1#
#160
0"
#162
0#
#165
1"
#168
1#
#170
0"
#175
1!
1"
#180
0"
#185
1"
#190
0"
#192
0#
#195
0!
1"
#200
0"
#205
1"
#210
0"
#215
1"
#216
1#
#220
0"
#222
0#
#225
1"
#228
1#
#230
0"
#235
1!
1"
#240
0"
#245
1"
#250
0"
#255
1"
#258
0#
#260
0"
#265
0!
1"
#270
0"
1#
#275
1!
1"
#280
0"
#285
1"
#288
0#
#290
0"
#295
0!
1"
#300
0"
#305
1"
#310
0"
#315
1"
#318
1#
#320
0"
#324
0#
#325
1"
#330
0"
#335
1"
#336
1#
#340
0"
#345
1!
1"
#348
0#
#350
0"
#355
0!
1"
#360
0"
#365
1"
#370
0"
#375
1"
#378
1#
#380
0"
#385
1!
1"
#390
0"
#395
1"
#400
0"
#405
1"
#408
0#
#410
0"
#415
0!
1"
#420
0"
1#
#425
1!
1"
#430
0"
#435
1"
#438
0#
#440
0"
#445
0!
1"
#450
0"
1#
#455
1!
1"
#460
0"
#462
0#
#465
0!
1"
#468
1#
#470
0"
#475
1!
1"
#480
0"
0#
#485
0!
1"
#486
1#
#490
0"
#495
1!
1"
#500
0"
#504
0#
#505
0!
1"
#510
0"
1#
#515
1!
1"
#520
0"
#522
0#
#525
0!
1"
#530
0"
#535
1"
#540
0"
#545
1"
#546
1#
#550
0"
#555
1!
1"
#558
0#
#560
0"
#565
0!
1"
#570
0"
1#
#575
1!
1"
#580
0"
#585
1"
#590
0"
#595
1"
#600
0"
0#
#605
0!
1"
#606
1#
#610
0"
#615
1!
1"
#620
0"
#624
0#
#625
0!
1"
#630
0"
#635
1"
#640
0"
#645
1"
#650
0"
#655
1"
#660
0"
#665
1"
#666
1#
#670
0"
#675
1!
1"
#680
0"
#685
1"
#690
0"
#695
1"
#696
0#
#700
0"
#702
1#
#705
1"
#710
0"
#714
0#
#715
0!
1"
#720
0"
#725
1"
#726
1#
#730
0"
#735
1!
1"
#738
0#
#740
0"
#744
1#
#745
1"
#750
0"
#755
1"
#760
0"
#765
1"
#768
0#
#770
0"
#775
0!
1"
#780
0"
#785
1"
#786
1#
#790
0"
#792
0#
#795
1"
#800
0"
#805
1"
#810
0"
1#
#815
1!
1"
#820
0"
#822
0#
#825
0!
1"
#830
0"
#834
1#
#835
1!
1"
#840
0"
0#
#845
0!
1"
#850
0"
#855
1"
#858
1#
#860
0"
#864
0#
#865
1"
#870
0"
#875
1"
#876
1#
#880
0"
#882
0#
#885
1"
#888
1#
#890
0"
#895
1!
1"
#900
0"
#905
1"
#910
0"
#915
1"
#918
0#
#920
0"
#925
0!
1"
#930
0"
#935
1"
#936
1#
#940
0"
#942
0#
#945
1"
#950
0"
#954
1#
#955
1!
1"
#960
0"
#965
1"
#966
0#
#970
0"
#975
0!
1"
#980
0"
#984
1#
#985
1!
1"
#990
0"
#995
1"
#996
0#
#1000
0"
#1005
0!
1"
