scripts/scripts/sv/signal_delay/dly_test1.sv
module dly_test1 (
  input wire clk,
  input wire sig,
  output reg sig_dly
);

always @(posedge clk)
  sig_dly <= repeat (5-1) @(posedge clk) sig;

endmodule

scripts/scripts/sv/signal_delay/dly_test0.sv
module dly_test0 (
  input wire clk,
  input wire sig,
  output bit sig_dly
);

bit sig_d1, sig_d2, sig_d3, sig_d4;
always @(posedge clk) begin
  sig_d1 <= sig;
  sig_d2 <= sig_d1;
  sig_d3 <= sig_d2;
  sig_d4 <= sig_d3;
  sig_dly <= sig_d4;
end

endmodule

scripts/scripts/sv/signal_delay/dly.sv
module tb ();

bit clk = 1'b0;
bit sig = 1'b0;
bit sig_dly0, sig_dly1;

always #5 clk <= !clk;

dly_test0 A0 (
  .clk (clk),
  .sig (sig),
  .sig_dly (sig_dly0)
);

dly_test1 A1 (
  .clk (clk),
  .sig (sig),
  .sig_dly (sig_dly1)
);

always @(posedge clk) begin
  #1;
  assert (sig_dly0 == sig_dly1) else 
    $error("sig_dly0:%b, sig_dly1:%b", sig_dly0, sig_dly1);
end

initial begin
  $dumpfile("dly.vcd");
  $dumpvars(0, tb);

  repeat(3) @(posedge clk);
  #1; sig = 1'b1;

  repeat(3) @(posedge clk);
  #1; sig = 1'b0;

  repeat(3) @(posedge clk);
  #1; sig = 1'b1;

  repeat(8) @(posedge clk);
  $finish;
end

endmodule

scripts/scripts/sv/signal_delay/dly.vcd
$date
	Mon Jan 31 15:02:57 2022
$end
$version
	Icarus Verilog
$end
$timescale
	1s
$end
$scope module tb $end
$var wire 1 ! sig_dly1 $end
$var wire 1 " sig_dly0 $end
$var reg 1 # clk $end
$var reg 1 $ sig $end
$scope module A0 $end
$var wire 1 # clk $end
$var wire 1 $ sig $end
$var reg 1 % sig_d1 $end
$var reg 1 & sig_d2 $end
$var reg 1 ' sig_d3 $end
$var reg 1 ( sig_d4 $end
$var reg 1 " sig_dly $end
$upscope $end
$scope module A1 $end
$var wire 1 # clk $end
$var wire 1 $ sig $end
$var reg 1 ) sig_dly $end
$upscope $end
$upscope $end
$enddefinitions $end
#0
$dumpvars
x)
0(
0'
0&
0%
0$
0#
0"
0!
$end
#5
1#
#10
0#
#15
1#
#20
0#
#25
1#
#26
1$
#30
0#
#35
1%
1#
#40
0#
#45
1&
0)
1#
#50
0#
#55
1'
1#
#56
0$
#60
0#
#65
1(
0%
1#
#70
0#
#75
1"
0&
1!
1)
1#
#80
0#
#85
0'
1#
#86
1$
#90
0#
#95
0(
1%
1#
#100
0#
#105
0"
1&
0!
0)
1#
#110
0#
#115
1'
1#
#120
0#
#125
1(
1#
#130
0#
#135
1"
1!
1)
1#
